rubber/__init__.py
rubber/biblio.py
rubber/cmdline.py
rubber/contents.py
rubber/convert.py
rubber/depend.py
rubber/dvip_tool.py
rubber/environment.py
rubber/index.py
rubber/module_interface.py
rubber/rules.ini
rubber/tex.py
rubber/util.py
rubber/version.py
rubber/converters/__init__.py
rubber/converters/compressor.py
rubber/converters/eps_gz.py
rubber/converters/fig2dev.py
rubber/converters/latex-1.5.1.py
rubber/converters/latex.py
rubber/converters/literate.py
rubber/converters/mpost.py
rubber/converters/shell.py
rubber/latex_modules/__init__.py
rubber/latex_modules/aleph.py
rubber/latex_modules/asymptote.py
rubber/latex_modules/backref.py
rubber/latex_modules/beamer.py
rubber/latex_modules/biblatex.py
rubber/latex_modules/bibtex.py
rubber/latex_modules/bibtopic.py
rubber/latex_modules/combine.py
rubber/latex_modules/dvipdfm.py
rubber/latex_modules/dvips.py
rubber/latex_modules/epsfig.py
rubber/latex_modules/glossaries.py
rubber/latex_modules/gnuplottex.py
rubber/latex_modules/graphics.py
rubber/latex_modules/graphicx.py
rubber/latex_modules/hyperref.py
rubber/latex_modules/index.py
rubber/latex_modules/listings.py
rubber/latex_modules/ltxtable.py
rubber/latex_modules/lualatex.py
rubber/latex_modules/makeidx.py
rubber/latex_modules/minitoc-hyper.py
rubber/latex_modules/minitoc.py
rubber/latex_modules/moreverb.py
rubber/latex_modules/multibib.py
rubber/latex_modules/nomencl.py
rubber/latex_modules/ntheorem.py
rubber/latex_modules/omega.py
rubber/latex_modules/pdftex.py
rubber/latex_modules/ps2pdf.py
rubber/latex_modules/pythontex.py
rubber/latex_modules/verbatim.py
rubber/latex_modules/vtex.py
rubber/latex_modules/xelatex.py
rubber/latex_modules/xr.py
latex_rubber-1.6.7.data/data/share/doc/rubber/rubber.html
latex_rubber-1.6.7.data/data/share/doc/rubber/rubber.info
latex_rubber-1.6.7.data/data/share/doc/rubber/rubber.pdf
latex_rubber-1.6.7.data/data/share/doc/rubber/rubber.texi
latex_rubber-1.6.7.data/data/share/doc/rubber/rubber.txt
latex_rubber-1.6.7.dist-info/METADATA
latex_rubber-1.6.7.dist-info/WHEEL
latex_rubber-1.6.7.dist-info/entry_points.txt
latex_rubber-1.6.7.dist-info/licenses/COPYING
latex_rubber-1.6.7.dist-info/RECORD
