Metadata-Version: 2.3
Name: latex-rubber
Version: 1.6.7
Summary: an automated system for building LaTeX documents
Project-URL: Homepage, https://gitlab.com/latex-rubber/rubber
Author-email: Sebastian Kapfer <sebastian.kapfer@fau.de>
Maintainer-email: Florian Schmaus <flo@geekplace.eu>
License: GPL-3.0-or-later
Requires-Python: >=3.8
